{
    "questions": [{
            "question": "What is the meaning of 'abundant'?",
            "options": ["Jarang", "Melimpah", "Terbatas", "Langka"],
            "correctIndex": 1
        },
        {
            "question": "What is the meaning of 'prevent'?",
            "options": ["Mengizinkan", "Mendorong", "Menghentikan", "Memulai"],
            "correctIndex": 2
        },
        {
            "question": "What is the meaning of 'diligent'?",
            "options": ["Tekun", "Ceroboh", "Malas", "Santai"],
            "correctIndex": 0
        },
        {
            "question": "What is the meaning of 'significant'?",
            "options": ["Kecil", "Tidak penting", "Penting", "Acak"],
            "correctIndex": 2
        },
        {
            "question": "What is the meaning of 'contribute'?",
            "options": ["Menghindari", "Berkontribusi", "Menyembunyikan", "Menipu"],
            "correctIndex": 1
        },
        {
            "question": "What is the meaning of 'devastate'?",
            "options": ["Memperbaiki", "Mengabaikan", "Merusak", "Menenangkan"],
            "correctIndex": 2
        },
        {
            "question": "What is the meaning of 'reluctant'?",
            "options": ["Antusias", "Percaya", "Terbuka", "Enggan"],
            "correctIndex": 3
        },
        {
            "question": "What is the meaning of 'confident'?",
            "options": ["Cemas", "Takut", "Ragu-ragu", "Percaya diri"],
            "correctIndex": 3
        },
        {
            "question": "What is the meaning of 'expand'?",
            "options": ["Memperluas", "Berkurang", "Mengecil", "Menyusut"],
            "correctIndex": 0
        },
        {
            "question": "What is the meaning of 'appreciate'?",
            "options": ["Meremehkan", "Menjauhi", "Menghargai", "Menyalahkan"],
            "correctIndex": 2
        },
        {
            "question": "What is the meaning of 'acquire'?",
            "options": ["Kehilangan", "Mendapatkan", "Melepaskan", "Menyerah"],
            "correctIndex": 1
        },
        {
            "question": "What is the meaning of 'comprehend'?",
            "options": ["Mengingat", "Memahami", "Mengevaluasi", "Mengabaikan"],
            "correctIndex": 1
        },
        {
            "question": "What is the meaning of 'cooperate'?",
            "options": ["Bersaing", "Berselisih", "Berpisah", "Bekerjasama"],
            "correctIndex": 3
        },
        {
            "question": "What is the meaning of 'grateful'?",
            "options": ["Kecewa", "Marah", "Terkesan", "Bersyukur"],
            "correctIndex": 3
        },
        {
            "question": "What is the meaning of 'persuade'?",
            "options": ["Merayu", "Menghukum", "Menghina", "Menyusahkan"],
            "correctIndex": 0
        },
        {
            "question": "What is the meaning of 'negotiate'?",
            "options": ["Berpisah", "Berdebat", "Bernegosiasi", "Bermusuhan"],
            "correctIndex": 2
        },
        {
            "question": "What is the meaning of 'recruit'?",
            "options": ["Membatalkan", "Memecat", "Mengundurkan diri", "Merekrut"],
            "correctIndex": 3
        },
        {
            "question": "What is the meaning of 'evaluate'?",
            "options": ["Menghancurkan", "Menyesatkan", "Menilai", "Membela"],
            "correctIndex": 2
        },
        {
            "question": "What is the meaning of 'integrate'?",
            "options": ["Membagi", "Mengisolasi", "Menggabungkan", "Menyembunyikan"],
            "correctIndex": 2
        },
        {
            "question": "What is the meaning of 'convey'?",
            "options": ["Menyembunyikan", "Mengungkapkan", "Mencela", "Merusak"],
            "correctIndex": 1
        }
    ]
}